{
    "Version": "1.2",
    "Data": {
        "Source": "d:\\unreal projects\\kittil\\plugins\\jsbsimflightdynamicsmodel\\source\\jsbsimflightdynamicsmodel\\private\\uegroundcallback.cpp",
        "ProvidedModule": "",
        "PCH": "d:\\unreal projects\\kittil\\intermediate\\build\\win64\\x64\\kittil\\shipping\\engine\\sharedpch.engine.project.valapi.cpp20.h.pch",
        "Includes": [
            "d:\\unreal projects\\kittil\\plugins\\jsbsimflightdynamicsmodel\\intermediate\\build\\win64\\x64\\unrealgame\\shipping\\jsbsimflightdynamicsmodel\\definitions.jsbsimflightdynamicsmodel.h",
            "d:\\unreal projects\\kittil\\plugins\\jsbsimflightdynamicsmodel\\source\\jsbsimflightdynamicsmodel\\public\\uegroundcallback.h",
            "d:\\unreal projects\\kittil\\plugins\\jsbsimflightdynamicsmodel\\source\\thirdparty\\jsbsim\\include\\models\\fginertial.h",
            "c:\\program files\\microsoft visual studio\\2022\\community\\vc\\tools\\msvc\\14.38.33130\\include\\memory",
            "c:\\program files\\microsoft visual studio\\2022\\community\\vc\\tools\\msvc\\14.38.33130\\include\\typeinfo",
            "c:\\program files\\microsoft visual studio\\2022\\community\\vc\\tools\\msvc\\14.38.33130\\include\\vcruntime_typeinfo.h",
            "c:\\program files\\microsoft visual studio\\2022\\community\\vc\\tools\\msvc\\14.38.33130\\include\\vcruntime_exception.h",
            "c:\\program files\\microsoft visual studio\\2022\\community\\vc\\tools\\msvc\\14.38.33130\\include\\eh.h",
            "c:\\program files (x86)\\windows kits\\10\\include\\10.0.19041.0\\ucrt\\corecrt_terminate.h",
            "d:\\unreal projects\\kittil\\plugins\\jsbsimflightdynamicsmodel\\source\\thirdparty\\jsbsim\\include\\models\\fgmodel.h",
            "c:\\program files\\microsoft visual studio\\2022\\community\\vc\\tools\\msvc\\14.38.33130\\include\\string",
            "c:\\program files\\microsoft visual studio\\2022\\community\\vc\\tools\\msvc\\14.38.33130\\include\\xstring",
            "c:\\program files\\microsoft visual studio\\2022\\community\\vc\\tools\\msvc\\14.38.33130\\include\\__msvc_sanitizer_annotate_container.hpp",
            "c:\\program files\\microsoft visual studio\\2022\\community\\vc\\tools\\msvc\\14.38.33130\\include\\xpolymorphic_allocator.h",
            "c:\\program files\\microsoft visual studio\\2022\\community\\vc\\tools\\msvc\\14.38.33130\\include\\cctype",
            "d:\\unreal projects\\kittil\\plugins\\jsbsimflightdynamicsmodel\\source\\thirdparty\\jsbsim\\include\\math\\fgmodelfunctions.h",
            "d:\\unreal projects\\kittil\\plugins\\jsbsimflightdynamicsmodel\\source\\thirdparty\\jsbsim\\include\\fgjsbbase.h",
            "c:\\program files\\microsoft visual studio\\2022\\community\\vc\\tools\\msvc\\14.38.33130\\include\\queue",
            "c:\\program files\\microsoft visual studio\\2022\\community\\vc\\tools\\msvc\\14.38.33130\\include\\deque",
            "c:\\program files\\microsoft visual studio\\2022\\community\\vc\\tools\\msvc\\14.38.33130\\include\\vector",
            "c:\\program files\\microsoft visual studio\\2022\\community\\vc\\tools\\msvc\\14.38.33130\\include\\__msvc_bit_utils.hpp",
            "c:\\program files\\microsoft visual studio\\2022\\community\\vc\\tools\\msvc\\14.38.33130\\include\\cmath",
            "c:\\program files\\microsoft visual studio\\2022\\community\\vc\\tools\\msvc\\14.38.33130\\include\\stdexcept",
            "c:\\program files\\microsoft visual studio\\2022\\community\\vc\\tools\\msvc\\14.38.33130\\include\\random",
            "c:\\program files\\microsoft visual studio\\2022\\community\\vc\\tools\\msvc\\14.38.33130\\include\\__msvc_int128.hpp",
            "c:\\program files\\microsoft visual studio\\2022\\community\\vc\\tools\\msvc\\14.38.33130\\include\\ios",
            "c:\\program files\\microsoft visual studio\\2022\\community\\vc\\tools\\msvc\\14.38.33130\\include\\xlocnum",
            "c:\\program files\\microsoft visual studio\\2022\\community\\vc\\tools\\msvc\\14.38.33130\\include\\streambuf",
            "c:\\program files\\microsoft visual studio\\2022\\community\\vc\\tools\\msvc\\14.38.33130\\include\\xiosbase",
            "c:\\program files (x86)\\windows kits\\10\\include\\10.0.19041.0\\ucrt\\share.h",
            "c:\\program files\\microsoft visual studio\\2022\\community\\vc\\tools\\msvc\\14.38.33130\\include\\system_error",
            "c:\\program files\\microsoft visual studio\\2022\\community\\vc\\tools\\msvc\\14.38.33130\\include\\__msvc_system_error_abi.hpp",
            "c:\\program files\\microsoft visual studio\\2022\\community\\vc\\tools\\msvc\\14.38.33130\\include\\cerrno",
            "c:\\program files\\microsoft visual studio\\2022\\community\\vc\\tools\\msvc\\14.38.33130\\include\\xcall_once.h",
            "c:\\program files\\microsoft visual studio\\2022\\community\\vc\\tools\\msvc\\14.38.33130\\include\\xerrc.h",
            "c:\\program files\\microsoft visual studio\\2022\\community\\vc\\tools\\msvc\\14.38.33130\\include\\xlocale",
            "c:\\program files\\microsoft visual studio\\2022\\community\\vc\\tools\\msvc\\14.38.33130\\include\\xfacet",
            "c:\\program files\\microsoft visual studio\\2022\\community\\vc\\tools\\msvc\\14.38.33130\\include\\xlocinfo",
            "c:\\program files\\microsoft visual studio\\2022\\community\\vc\\tools\\msvc\\14.38.33130\\include\\__msvc_xlocinfo_types.hpp",
            "c:\\program files\\microsoft visual studio\\2022\\community\\vc\\tools\\msvc\\14.38.33130\\include\\clocale",
            "c:\\program files (x86)\\windows kits\\10\\include\\10.0.19041.0\\ucrt\\locale.h",
            "c:\\program files\\microsoft visual studio\\2022\\community\\vc\\tools\\msvc\\14.38.33130\\include\\xbit_ops.h",
            "c:\\program files\\microsoft visual studio\\2022\\community\\vc\\tools\\msvc\\14.38.33130\\include\\chrono",
            "c:\\program files\\microsoft visual studio\\2022\\community\\vc\\tools\\msvc\\14.38.33130\\include\\__msvc_chrono.hpp",
            "c:\\program files\\microsoft visual studio\\2022\\community\\vc\\tools\\msvc\\14.38.33130\\include\\ratio",
            "c:\\program files\\microsoft visual studio\\2022\\community\\vc\\tools\\msvc\\14.38.33130\\include\\xfilesystem_abi.h",
            "c:\\program files\\microsoft visual studio\\2022\\community\\vc\\tools\\msvc\\14.38.33130\\include\\__msvc_tzdb.hpp",
            "c:\\program files\\microsoft visual studio\\2022\\community\\vc\\tools\\msvc\\14.38.33130\\include\\forward_list",
            "c:\\program files\\microsoft visual studio\\2022\\community\\vc\\tools\\msvc\\14.38.33130\\include\\istream",
            "c:\\program files\\microsoft visual studio\\2022\\community\\vc\\tools\\msvc\\14.38.33130\\include\\ostream",
            "c:\\program files\\microsoft visual studio\\2022\\community\\vc\\tools\\msvc\\14.38.33130\\include\\optional",
            "c:\\program files\\microsoft visual studio\\2022\\community\\vc\\tools\\msvc\\14.38.33130\\include\\xsmf_control.h",
            "c:\\program files\\microsoft visual studio\\2022\\community\\vc\\tools\\msvc\\14.38.33130\\include\\sstream",
            "c:\\program files\\microsoft visual studio\\2022\\community\\vc\\tools\\msvc\\14.38.33130\\include\\xloctime",
            "c:\\program files\\microsoft visual studio\\2022\\community\\vc\\tools\\msvc\\14.38.33130\\include\\format",
            "c:\\program files\\microsoft visual studio\\2022\\community\\vc\\tools\\msvc\\14.38.33130\\include\\__msvc_format_ucd_tables.hpp",
            "c:\\program files\\microsoft visual studio\\2022\\community\\vc\\tools\\msvc\\14.38.33130\\include\\__msvc_print.hpp",
            "c:\\program files\\microsoft visual studio\\2022\\community\\vc\\tools\\msvc\\14.38.33130\\include\\bit",
            "c:\\program files\\microsoft visual studio\\2022\\community\\vc\\tools\\msvc\\14.38.33130\\include\\charconv",
            "c:\\program files\\microsoft visual studio\\2022\\community\\vc\\tools\\msvc\\14.38.33130\\include\\xcharconv.h",
            "c:\\program files\\microsoft visual studio\\2022\\community\\vc\\tools\\msvc\\14.38.33130\\include\\xcharconv_ryu.h",
            "c:\\program files\\microsoft visual studio\\2022\\community\\vc\\tools\\msvc\\14.38.33130\\include\\xcharconv_ryu_tables.h",
            "c:\\program files\\microsoft visual studio\\2022\\community\\vc\\tools\\msvc\\14.38.33130\\include\\xcharconv_tables.h",
            "c:\\program files\\microsoft visual studio\\2022\\community\\vc\\tools\\msvc\\14.38.33130\\include\\locale",
            "c:\\program files\\microsoft visual studio\\2022\\community\\vc\\tools\\msvc\\14.38.33130\\include\\xlocbuf",
            "c:\\program files\\microsoft visual studio\\2022\\community\\vc\\tools\\msvc\\14.38.33130\\include\\xlocmes",
            "c:\\program files\\microsoft visual studio\\2022\\community\\vc\\tools\\msvc\\14.38.33130\\include\\xlocmon",
            "c:\\program files\\microsoft visual studio\\2022\\community\\vc\\tools\\msvc\\14.38.33130\\include\\iomanip",
            "d:\\unreal projects\\kittil\\plugins\\jsbsimflightdynamicsmodel\\source\\thirdparty\\jsbsim\\include\\jsbsim_api.h",
            "d:\\unreal projects\\kittil\\plugins\\jsbsimflightdynamicsmodel\\source\\thirdparty\\jsbsim\\include\\input_output\\string_utilities.h",
            "d:\\unreal projects\\kittil\\plugins\\jsbsimflightdynamicsmodel\\source\\thirdparty\\jsbsim\\include\\input_output\\fgpropertyreader.h",
            "c:\\program files\\microsoft visual studio\\2022\\community\\vc\\tools\\msvc\\14.38.33130\\include\\map",
            "c:\\program files\\microsoft visual studio\\2022\\community\\vc\\tools\\msvc\\14.38.33130\\include\\xtree",
            "c:\\program files\\microsoft visual studio\\2022\\community\\vc\\tools\\msvc\\14.38.33130\\include\\xnode_handle.h",
            "d:\\unreal projects\\kittil\\plugins\\jsbsimflightdynamicsmodel\\source\\thirdparty\\jsbsim\\include\\simgear\\props\\props.hxx",
            "c:\\program files\\microsoft visual studio\\2022\\community\\vc\\tools\\msvc\\14.38.33130\\include\\iostream",
            "d:\\unreal projects\\kittil\\plugins\\jsbsimflightdynamicsmodel\\source\\thirdparty\\jsbsim\\include\\simgear\\compiler.h",
            "d:\\unreal projects\\kittil\\plugins\\jsbsimflightdynamicsmodel\\source\\thirdparty\\jsbsim\\include\\simgear\\structure\\sgreferenced.hxx",
            "d:\\unreal projects\\kittil\\plugins\\jsbsimflightdynamicsmodel\\source\\thirdparty\\jsbsim\\include\\simgear\\structure\\sgsharedptr.hxx",
            "d:\\unreal projects\\kittil\\plugins\\jsbsimflightdynamicsmodel\\source\\thirdparty\\jsbsim\\include\\input_output\\fgpropertymanager.h",
            "c:\\program files\\microsoft visual studio\\2022\\community\\vc\\tools\\msvc\\14.38.33130\\include\\list",
            "d:\\unreal projects\\kittil\\plugins\\jsbsimflightdynamicsmodel\\source\\thirdparty\\jsbsim\\include\\simgear\\misc\\sg_path.hxx",
            "d:\\unreal projects\\kittil\\plugins\\jsbsimflightdynamicsmodel\\source\\thirdparty\\jsbsim\\include\\math\\fglocation.h",
            "c:\\program files\\microsoft visual studio\\2022\\community\\vc\\tools\\msvc\\14.38.33130\\include\\cassert",
            "c:\\program files (x86)\\windows kits\\10\\include\\10.0.19041.0\\ucrt\\assert.h",
            "d:\\unreal projects\\kittil\\plugins\\jsbsimflightdynamicsmodel\\source\\thirdparty\\jsbsim\\include\\math\\fgcolumnvector3.h",
            "d:\\unreal projects\\kittil\\plugins\\jsbsimflightdynamicsmodel\\source\\thirdparty\\jsbsim\\include\\math\\fgmatrix33.h",
            "d:\\unreal projects\\kittil\\plugins\\jsbsimflightdynamicsmodel\\source\\thirdparty\\jsbsim\\include\\input_output\\fggroundcallback.h",
            "d:\\unreal projects\\kittil\\plugins\\jsbsimflightdynamicsmodel\\source\\jsbsimflightdynamicsmodel\\public\\jsbsimmovementcomponent.h",
            "d:\\unreal projects\\kittil\\plugins\\jsbsimflightdynamicsmodel\\source\\jsbsimflightdynamicsmodel\\public\\jsbsimmodule.h",
            "d:\\unreal projects\\kittil\\plugins\\jsbsimflightdynamicsmodel\\source\\jsbsimflightdynamicsmodel\\public\\fdmtypes.h",
            "d:\\unreal projects\\kittil\\plugins\\jsbsimflightdynamicsmodel\\intermediate\\build\\win64\\unrealgame\\inc\\jsbsimflightdynamicsmodel\\uht\\fdmtypes.generated.h",
            "d:\\unreal projects\\kittil\\plugins\\jsbsimflightdynamicsmodel\\intermediate\\build\\win64\\unrealgame\\inc\\jsbsimflightdynamicsmodel\\uht\\jsbsimmovementcomponent.generated.h"
        ],
        "ImportedModules": [],
        "ImportedHeaderUnits": []
    }
}